.gitignore
.travis.yml
Dockerfile
README.md
runtests.py
setup.py
doc/.gitignore
doc/examplerc.sample
doc/full_example.sh
doc/simple_example.sh
src/chisubmit/__init__.py
src/chisubmit.egg-info/PKG-INFO
src/chisubmit.egg-info/SOURCES.txt
src/chisubmit.egg-info/dependency_links.txt
src/chisubmit.egg-info/entry_points.txt
src/chisubmit.egg-info/not-zip-safe
src/chisubmit.egg-info/requires.txt
src/chisubmit.egg-info/top_level.txt
src/chisubmit/backend/__init__.py
src/chisubmit/backend/manage.py
src/chisubmit/backend/urls.py
src/chisubmit/backend/wsgi.py
src/chisubmit/backend/api/__init__.py
src/chisubmit/backend/api/admin.py
src/chisubmit/backend/api/helpers.py
src/chisubmit/backend/api/models.py
src/chisubmit/backend/api/serializers.py
src/chisubmit/backend/api/urls.py
src/chisubmit/backend/api/views.py
src/chisubmit/backend/api/fixtures/admin_user.yaml
src/chisubmit/backend/api/fixtures/course1.yaml
src/chisubmit/backend/api/fixtures/course1_pa1.yaml
src/chisubmit/backend/api/fixtures/course1_pa1_grades.yaml
src/chisubmit/backend/api/fixtures/course1_pa1_registrations.yaml
src/chisubmit/backend/api/fixtures/course1_pa1_registrations_with_submissions.yaml
src/chisubmit/backend/api/fixtures/course1_pa2.yaml
src/chisubmit/backend/api/fixtures/course1_teams.yaml
src/chisubmit/backend/api/fixtures/course1_users.yaml
src/chisubmit/backend/api/fixtures/course2.yaml
src/chisubmit/backend/api/fixtures/course2_hw1.yaml
src/chisubmit/backend/api/fixtures/course2_hw2.yaml
src/chisubmit/backend/api/fixtures/course2_users.yaml
src/chisubmit/backend/api/fixtures/users.yaml
src/chisubmit/backend/api/migrations/0001_initial.py
src/chisubmit/backend/api/migrations/0002_connstr_length.py
src/chisubmit/backend/api/migrations/0003_add_grace_period.py
src/chisubmit/backend/api/migrations/0004_validate_extensions_used.py
src/chisubmit/backend/api/migrations/0005_add_archived_courses.py
src/chisubmit/backend/api/migrations/0006_submission_submitted_by.py
src/chisubmit/backend/api/migrations/0007_registration_grading_started.py
src/chisubmit/backend/api/migrations/0008_python3+django2_upgrade.py
src/chisubmit/backend/api/migrations/0009_gradescope.py
src/chisubmit/backend/api/migrations/__init__.py
src/chisubmit/backend/settings/.gitignore
