Metadata-Version: 2.1
Name: chisubmit
Version: 2.1.0
Summary: A system for managing assignments and teams in university courses
Home-page: http://chi.cs.uchicago.edu/chisubmit/
Author: University of Chicago, Department of Computer Science
Author-email: borja@cs.uchicago.edu
License: Apache Software License
Platform: UNKNOWN
Classifier: Development Status :: 5 - Production/Stable
Classifier: Environment :: Console
Classifier: Intended Audience :: Developers
Classifier: Intended Audience :: System Administrators
Classifier: Intended Audience :: Education
Classifier: License :: OSI Approved :: BSD License
Classifier: Operating System :: POSIX
Classifier: Programming Language :: Python :: 3 :: Only
Classifier: Topic :: Education
Requires-Python: >=3.5
Provides-Extra: server
